uvs/__init__.py
uvs/config.py
uvs/core.py
uvs/git_utils.py
uvs/main.py
uvs/metadata.py
uvs/path_manager.py
uvs-0.1.0.dist-info/METADATA
uvs-0.1.0.dist-info/WHEEL
uvs-0.1.0.dist-info/entry_points.txt
uvs-0.1.0.dist-info/RECORD
