Metadata-Version: 2.4
Name: uvs
Version: 0.1.0
Summary: Manage Python scripts using `uv` from GitHub Gists and local files
Author-email: Adam McKay <adam@beepboop.digital>
Requires-Python: >=3.11
Requires-Dist: gitpython>=3.1.0
Requires-Dist: rich>=13.0.0
Requires-Dist: tomli-w>=1.0.0
Requires-Dist: typer>=0.9.0
